stealthbot/.DS_Store
stealthbot/__init__.py
stealthbot/_id.py
stealthbot/accept_google_cookies.py
stealthbot/anti_detect_driver.py
stealthbot/anti_detect_driver_selenium_wire.py
stealthbot/anti_detect_requests.py
stealthbot/base_data.py
stealthbot/beep_utils.py
stealthbot/cache.py
stealthbot/calc_max_parallel_browsers.py
stealthbot/check_and_download_driver.py
stealthbot/close_chrome.py
stealthbot/create_driver_utils.py
stealthbot/creators.py
stealthbot/decorators.py
stealthbot/decorators_utils.py
stealthbot/download_driver.py
stealthbot/driver_about.py
stealthbot/formats.py
stealthbot/get_chrome_version.py
stealthbot/ip_utils.py
stealthbot/json_finder.py
stealthbot/list_utils.py
stealthbot/local_storage.py
stealthbot/local_storage_driver.py
stealthbot/opponent.py
stealthbot/output.py
stealthbot/profile.py
stealthbot/st.py
stealthbot/temp_mail.py
stealthbot/usage.py
stealthbot/user_agent.py
stealthbot/user_generator.py
stealthbot/utils.py
stealthbot/wait.py
stealthbot/window_size.py
stealthbot-0.1.6.dist-info/WHEEL
stealthbot-0.1.6.dist-info/METADATA
stealthbot-0.1.6.dist-info/RECORD
